argos_track/__init__.py
argos_track/__main__.py
argos_track/batchtrack.py
argos_track/sortracker.py
argos_track/sortrackerwidget.py
argos_track/track.py
argos_tracker-0.1.1.dist-info/LICENSE
argos_tracker-0.1.1.dist-info/METADATA
argos_tracker-0.1.1.dist-info/WHEEL
argos_tracker-0.1.1.dist-info/top_level.txt
argos_tracker-0.1.1.dist-info/RECORD
